gluex_rcdb/__init__.py
gluex_rcdb/__init__.pyi
gluex_rcdb/gluex_rcdb.pypy311-pp73-ppc_64-linux-gnu.so
gluex_rcdb/py.typed
gluex_rcdb-0.1.8.dist-info/METADATA
gluex_rcdb-0.1.8.dist-info/WHEEL
gluex_rcdb-0.1.8.dist-info/RECORD
