Metadata-Version: 2.4
Name: gluex-rcdb
Version: 0.1.8
Classifier: License :: OSI Approved :: Apache Software License
Classifier: License :: OSI Approved :: MIT License
Classifier: Programming Language :: Python :: 3
Classifier: Programming Language :: Python :: 3.8
Classifier: Programming Language :: Python :: 3.9
Classifier: Programming Language :: Python :: 3.10
Classifier: Programming Language :: Python :: 3.11
Classifier: Programming Language :: Python :: 3.12
Classifier: Programming Language :: Rust
Classifier: Programming Language :: Python :: Implementation :: CPython
Classifier: Programming Language :: Python :: Implementation :: PyPy
Requires-Dist: pytest ; extra == 'tests'
Provides-Extra: tests
Summary: Python bindings for the GlueX Run Condition Database
Keywords: gluex,rcdb,sqlite,conditions
Home-Page: https://github.com/denehoffman/gluex-rs
Author-email: Nathaniel Dene Hoffman <dene@cmu.edu>
License: Apache-2.0 OR MIT
Requires-Python: >=3.8
Project-URL: Documentation, https://github.com/denehoffman/gluex-rs/tree/main/crates/gluex-rcdb-py
Project-URL: Homepage, https://github.com/denehoffman/gluex-rs
Project-URL: Issues, https://github.com/denehoffman/gluex-rs/issues
Project-URL: Repository, https://github.com/denehoffman/gluex-rs
